Lab5/Lab5_student_code/mult16_pipelined.v
`timescale 1ns / 1ps

module mult16_pipelined(
    input               clk,
    input               rstn,
    input       [15:0]  A,
    input       [15:0]  B,
    output  reg [31:0]  result
    );

    // Make each Stage
    // Capture input
    reg [15:0]   A_capture;
    reg [15:0]   B_capture;

    // pipelined stage
    reg [11:0]   stage_1st   [7:0];
    reg [16:0]   stage_2nd   [3:0];
    reg [25:0]   stage_3rd   [1:0];
    reg [34:0]   stage_4th;

    integer i;

    always @(posedge clk or negedge rstn) begin
        if(!rstn)begin
            A_capture <= 16'd0;
            B_capture <= 16'd0;

            for(i=0; i<8; i=i+1)begin
                stage_1st[i] <= 12'd0;
            end
            for(i=0; i<4; i=i+1)begin
                stage_2nd[i] <= 17'd0;
            end
            for(i=0; i<2; i=i+1)begin
                stage_3rd[i] <= 31'd0;
            end

            stage_4th <= 35'd0;
            result <= 32'd0;
        end
        else begin
            A_capture    <= A;
            B_capture    <= B;

            stage_1st[0] <= A[7:0] * B[3:0];
            stage_1st[1] <= A[7:0] * B[7:4];
            stage_1st[2] <= A[7:0] * B[11:8];
            stage_1st[3] <= A[7:0] * B[15:12];
            stage_1st[4] <= A[15:8] * B[3:0];
            stage_1st[5] <= A[15:8] * B[7:4];
            stage_1st[6] <= A[15:8] * B[11:8];
            stage_1st[7] <= A[15:8] * B[15:12];

            stage_2nd[0] <= {4'b0, stage_1st[0]} + {stage_1st[1], 4'b0};
            stage_2nd[1] <= {4'b0, stage_1st[2]} + {stage_1st[3], 4'b0};
            stage_2nd[2] <= {4'b0, stage_1st[4]} + {stage_1st[5], 4'b0};
            stage_2nd[3] <= {4'b0, stage_1st[6]} + {stage_1st[7], 4'b0};
           
            stage_3rd[0] <= {8'b0, stage_2nd[0]} + {stage_2nd[1], 8'b0};
            stage_3rd[1] <= {8'b0, stage_2nd[2]} + {stage_2nd[3], 8'b0};

            stage_4th    <= {8'b0, stage_3rd[0]} + {stage_3rd[1], 8'b0};
           
            result       <= stage_4th[31:0];
        end
    end


endmodule

Lab5/Lab5_student_code/tb_mult16_pipelined.v
`timescale 1ns / 1ps

`define HALF_CLK_PERIOD 100
`define FULL_CLK_PERIOD (2*`HALF_CLK_PERIOD)
`define INPUT_DELAY     (`HALF_CLK_PERIOD)
`define OUTPUT_DELAY    (2*`HALF_CLK_PERIOD - 0.1)

module tb_mult16_pipelined();
    reg clk;
    reg rstn;
    reg [15:0]  A;
    reg [15:0]  B;
    wire [31:0]  result;

    integer i;
    integer valid;

    mult16_pipelined #() u_mult16_pipelined(
        .clk(clk),
        .rstn(rstn),
        .A(A),
        .B(B),
        .result(result)
    );

    initial begin
        clk = 1'd1;
        forever begin
            #(`HALF_CLK_PERIOD) clk = ~clk;
        end
    end

    initial begin
        $dumpfile("wave.vcd");
        $dumpvars(0, u_mult16_pipelined);

        rstn = 1'd0;
        A = 16'd0;
        B = 16'd0;

        @(posedge clk)
        #(`INPUT_DELAY)
        rstn = 1'd1;
        for(i=0;i<20;i=i+1)  @(posedge clk);

        @(posedge clk)
        #(`INPUT_DELAY)
        A = 16'd14;
        B = 16'd16;

        @(posedge clk)
        #(`INPUT_DELAY)
        A = 16'd256;
        B = 16'd237;
        
        @(posedge clk)
        #(`INPUT_DELAY)
        A = 16'd125;
        B = 16'd236;

        for(i=0;i<20;i=i+1)  @(posedge clk);
        $finish;
    end

    initial begin
        valid = 1;

        @(posedge clk)
        repeat(20) @(posedge clk);
        @(posedge clk)
        //1st input inserted
        @(posedge clk)
        //1st input captured
        repeat(4) @(posedge clk);
        @(posedge clk)
        #(`OUTPUT_DELAY)
        $display("result: %d\nanswer: %d\n", result, 32'd224);
        if(result !== 32'd224)begin
            valid = 0;
        end

        @(posedge clk)
        #(`OUTPUT_DELAY)
        $display("result: %d\nanswer: %d\n", result, 32'd60672);
        if(result !== 32'd60672)begin
            valid = 0;
        end

        @(posedge clk)
        #(`OUTPUT_DELAY)
        $display("result: %d\nanswer: %d\n", result, 32'd29500);
        if(result !== 32'd29500)begin
            valid = 0;
        end

        if(valid) $display("###########################\n[Result]: Result is correct.\n###########################");
        else $display("!!!!!!!!!!!!!!!!!!!!!!!!!!!\n[Result]: Result is Fail Fail Fail Fail ((<o>, ... ,<o>)).\n!!!!!!!!!!!!!!!!!!!!!!!!!!!");
    end

endmodule

Lab5/Lab5_student_code/wave.vcd
$date
	Mon Oct 10 20:08:50 2022
$end
$version
	Icarus Verilog
$end
$timescale
	1ps
$end
$scope module tb_mult16_pipelined $end
$scope module u_mult16_pipelined $end
$var wire 16 ! A [15:0] $end
$var wire 16 " B [15:0] $end
$var wire 1 # clk $end
$var wire 1 $ rstn $end
$var reg 16 % A_capture [15:0] $end
$var reg 16 & B_capture [15:0] $end
$var reg 32 ' result [31:0] $end
$var reg 35 ( stage_4th [34:0] $end
$var integer 32 ) i [31:0] $end
$upscope $end
$upscope $end
$enddefinitions $end
#0
$dumpvars
b10 )
b0 (
b0 '
b0 &
b0 %
0$
1#
b0 "
b0 !
$end
#100000
0#
#200000
b10 )
1#
#300000
1$
0#
#400000
1#
#500000
0#
#600000
1#
#700000
0#
#800000
1#
#900000
0#
#1000000
1#
#1100000
0#
#1200000
1#
#1300000
0#
#1400000
1#
#1500000
0#
#1600000
1#
#1700000
0#
#1800000
1#
#1900000
0#
#2000000
1#
#2100000
0#
#2200000
1#
#2300000
0#
#2400000
1#
#2500000
0#
#2600000
1#
#2700000
0#
#2800000
1#
#2900000
0#
#3000000
1#
#3100000
0#
#3200000
1#
#3300000
0#
#3400000
1#
#3500000
0#
#3600000
1#
#3700000
0#
#3800000
1#
#3900000
0#
#4000000
1#
#4100000
0#
#4200000
1#
#4300000
0#
#4400000
1#
#4500000
b10000 "
b1110 !
0#
#4600000
b10000 &
b1110 %
1#
#4700000
b11101101 "
b100000000 !
0#
#4800000
b11101101 &
b100000000 %
1#
#4900000
b11101100 "
b1111101 !
0#
#5000000
b11101100 &
b1111101 %
1#
#5100000
0#
#5200000
1#
#5300000
0#
#5400000
b11100000 (
1#
#5500000
0#
#5600000
b11100000 '
b1110110100000000 (
1#
#5700000
0#
#5800000
b1110110100000000 '
b111001100111100 (
1#
#5900000
0#
#6000000
b111001100111100 '
1#
